{
    "patches":[
        {
            "id": 1,
            "name": "bloop",
            "oscillators": [
                {
                    "name": 1,
                    "type": "triangle",
                    "gain": 0.5,
                    "attack": 0.5,
                    "decay": 0.5,
                    "sustain": 0.5,
                    "release": 0.5
                },
                {
                    "name": 2,
                    "type": "sine",
                    "gain": 0.5,
                    "attack": 0.5,
                    "decay": 0.5,
                    "sustain": 0.5,
                    "release": 0.5
                },
                {
                    "name": 3,
                    "type": "sawtooth",
                    "gain": 0.5,
                    "attack": 0.5,
                    "decay": 0.5,
                    "sustain": 0.5,
                    "release": 0.5
                }
            ]
        }
    ]
}